pyComBat/__init__.py
pyComBat/utils.py
pyComBat_test-0.1.2.dist-info/COPYING
pyComBat_test-0.1.2.dist-info/LICENSE
pyComBat_test-0.1.2.dist-info/METADATA
pyComBat_test-0.1.2.dist-info/WHEEL
pyComBat_test-0.1.2.dist-info/top_level.txt
pyComBat_test-0.1.2.dist-info/RECORD
