Metadata-Version: 2.1
Name: pyComBat-test
Version: 0.1.2
Summary: pyComBat, a Python tool for batch effects correction in high-throughput molecular data using empirical Bayes methods
Home-page: https://github.com/epigenelabs/pyComBat
Author: Abdelkader Behdenna
Author-email: abdelkader@epigenelabs.com
License: UNKNOWN
Platform: UNKNOWN
Classifier: Programming Language :: Python :: 3
Classifier: License :: OSI Approved :: GNU General Public License v3 or later (GPLv3+)
Classifier: Operating System :: OS Independent
Requires-Python: >=3.6
